Workbook

Sheet Cover
B2: INVENTORY OPTIMIZER & SPC CONTROL PLAN
B3: DistributorCo Lean Shield -- DMAIC Track 1 v3
B5: Headline Findings
B7: First Class shipping late rate | C7: 95.3%
B8: Standard Class Cpk | C8: 0.001 (NOT CAPABLE)
B9: Second Class Cpk | C9: -0.469 (OUT OF SPEC)
B10: Top-10 SKU EOQ savings (annual) | C10: $50,629
B11: PENDING_PAYMENT bottleneck share | C11: 22.1%
B12: Margin erosion per late order | C12: $0.78
B15: Sheet Map
B17: Inputs | C17: Assumptions: H_rate, S_cost, Z, lead times
B18: SKU_Data | C18: Top-10 SKU demand statistics (raw data)
B19: EOQ_Calc | C19: EOQ, Safety Stock, ROP -- live formulas
B20: SPC_Limits | C20: Per-mode control chart limits
B21: Control_Plan | C21: DMAIC Control Plan
B22: OEE_Grid | C22: OEE matrix: 4 modes x 5 markets
B23: Summary | C23: Executive KPIs
B27: Honest call-outs
B28: - DistributorCo is a synthetic anchor - per-order numbers real, firm scale narrated
B29: - "Bullwhip Effect" reframed as single-tier demand-signal distortion (dataset is single-tier)
B30: - First Class shipping has sigma=0 - Cpk is undefined; treated as deterministic process
B31: - Holding cost rate (20%) is industry-standard but firm-specific; adjust in Inputs!B6

Sheet Inputs
B2: INPUT ASSUMPTIONS
B3: Adjust these assumptions to recalculate the entire model.
B5: Parameter | C5: Value | D5: Notes
B6: Holding cost rate | C6: 0.2 | D6: 20% of unit price/yr (industry std)
B7: Order processing cost ($) | C7: 50 | D7: $50/PO (DistributorCo standard)
B8: Service-level Z (95%) | C8: 1.645 | D8: 95% one-sided
B9: Average lead time (days) | C9: 3.5 | D9: From Days for shipping (real)
B10: Avg orders per day | C10: 160 | D10: Firm-wide

Sheet SKU_Data
B2: TOP-10 SKU DEMAND STATISTICS
B3: Raw inputs from order history (1,126 days). Edit values in blue to test scenarios.
B5: SKU ID | C5: SKU Name | D5: Unit Price ($) | E5: Annual Demand | F5: Daily Std | G5: Lead Time (days)
B6: 365 | C6: Perfect Fitness Perfect Rip Deck | D6: 59.99 | E6: 23889 | F6: 27.64 | G6: 3.51
B7: 502 | C7: Nike Men's Dri-FIT Victory Golf Pol | D7: 50 | E7: 20407 | F7: 24.57 | G7: 3.48
B8: 1014 | C8: O'Brien Men's Neoprene Life Vest | D8: 49.98 | E8: 18737 | F8: 22.64 | G8: 3.5
B9: 191 | C9: Nike Men's Free 5.0+ Running Shoe | D9: 99.99 | E9: 11890 | F9: 16.06 | G9: 3.49
B10: 627 | C10: Under Armour Girls' Toddler Spine S | D10: 39.99 | E10: 10287 | F10: 14.04 | G10: 3.49
B11: 403 | C11: Nike Men's CJ Elite 2 TD Football C | D11: 129.99 | E11: 7211 | F11: 8.25 | G11: 3.5
B12: 1004 | C12: Field & Stream Sportsman 16 Gun Fir | D12: 399.98 | E12: 5616 | F12: 6.68 | G12: 3.5
B13: 1073 | C13: Pelican Sunstream 100 Kayak | D13: 199.99 | E13: 5024 | F13: 6.13 | G13: 3.48
B14: 957 | C14: Diamondback Women's Serene Classic | D14: 299.98 | E14: 4450 | F14: 5.51 | G14: 3.5
B15: 977 | C15: ENO Atlas Hammock Straps | D15: 29.99 | E15: 323 | F15: 1.91 | G15: 3.46

Sheet EOQ_Calc
B2: EOQ + SAFETY STOCK + REORDER POINT (LIVE FORMULAS)
B3: Formulas pull from Inputs and SKU_Data. Change inputs there to recalculate.
B5: SKU ID | C5: SKU Name | D5: Unit Price | E5: Annual Demand | F5: Holding Cost ($/unit/yr) | G5: EOQ (units) | H5: Safety Stock | I5: Reorder Point | J5: Current Cost ($/yr) | K5: EOQ Cost ($/yr) | L5: Annual Savings ($)
B6: =SKU_Data!B6 -> 365 | C6: =SKU_Data!C6 -> Perfect Fitness Perfect Rip Deck | D6: =SKU_Data!D6 -> 59.99 | E6: =SKU_Data!E6 -> 23889 | F6: =H_rate*D6 -> 11.998 | G6: =ROUND(SQRT(2*E6*S_cost/F6),0) -> 446 | H6: =ROUND(Z_service*SKU_Data!F6*SQRT(SKU_Data!G6),0) -> 85 | I6: =ROUND(E6/365*SKU_Data!G6+H6,0) -> 315 | J6: =ROUND(E6/(E6/12)*S_cost+(E6/12)/2*F6,0) -> 12543 | K6: =ROUND(E6/G6*S_cost+G6/2*F6,0) -> 5354 | L6: =J6-K6 -> 7189
B7: =SKU_Data!B7 -> 502 | C7: =SKU_Data!C7 -> Nike Men's Dri-FIT Victory Golf Pol | D7: =SKU_Data!D7 -> 50 | E7: =SKU_Data!E7 -> 20407 | F7: =H_rate*D7 -> 10 | G7: =ROUND(SQRT(2*E7*S_cost/F7),0) -> 452 | H7: =ROUND(Z_service*SKU_Data!F7*SQRT(SKU_Data!G7),0) -> 75 | I7: =ROUND(E7/365*SKU_Data!G7+H7,0) -> 270 | J7: =ROUND(E7/(E7/12)*S_cost+(E7/12)/2*F7,0) -> 9103 | K7: =ROUND(E7/G7*S_cost+G7/2*F7,0) -> 4517 | L7: =J7-K7 -> 4586
B8: =SKU_Data!B8 -> 1014 | C8: =SKU_Data!C8 -> O'Brien Men's Neoprene Life Vest | D8: =SKU_Data!D8 -> 49.98 | E8: =SKU_Data!E8 -> 18737 | F8: =H_rate*D8 -> 9.996 | G8: =ROUND(SQRT(2*E8*S_cost/F8),0) -> 433 | H8: =ROUND(Z_service*SKU_Data!F8*SQRT(SKU_Data!G8),0) -> 70 | I8: =ROUND(E8/365*SKU_Data!G8+H8,0) -> 250 | J8: =ROUND(E8/(E8/12)*S_cost+(E8/12)/2*F8,0) -> 8404 | K8: =ROUND(E8/G8*S_cost+G8/2*F8,0) -> 4328 | L8: =J8-K8 -> 4076
B9: =SKU_Data!B9 -> 191 | C9: =SKU_Data!C9 -> Nike Men's Free 5.0+ Running Shoe | D9: =SKU_Data!D9 -> 99.99 | E9: =SKU_Data!E9 -> 11890 | F9: =H_rate*D9 -> 19.998 | G9: =ROUND(SQRT(2*E9*S_cost/F9),0) -> 244 | H9: =ROUND(Z_service*SKU_Data!F9*SQRT(SKU_Data!G9),0) -> 49 | I9: =ROUND(E9/365*SKU_Data!G9+H9,0) -> 163 | J9: =ROUND(E9/(E9/12)*S_cost+(E9/12)/2*F9,0) -> 10507 | K9: =ROUND(E9/G9*S_cost+G9/2*F9,0) -> 4876 | L9: =J9-K9 -> 5631
B10: =SKU_Data!B10 -> 627 | C10: =SKU_Data!C10 -> Under Armour Girls' Toddler Spine S | D10: =SKU_Data!D10 -> 39.99 | E10: =SKU_Data!E10 -> 10287 | F10: =H_rate*D10 -> 7.998 | G10: =ROUND(SQRT(2*E10*S_cost/F10),0) -> 359 | H10: =ROUND(Z_service*SKU_Data!F10*SQRT(SKU_Data!G10),0) -> 43 | I10: =ROUND(E10/365*SKU_Data!G10+H10,0) -> 141 | J10: =ROUND(E10/(E10/12)*S_cost+(E10/12)/2*F10,0) -> 4028 | K10: =ROUND(E10/G10*S_cost+G10/2*F10,0) -> 2868 | L10: =J10-K10 -> 1160
B11: =SKU_Data!B11 -> 403 | C11: =SKU_Data!C11 -> Nike Men's CJ Elite 2 TD Football C | D11: =SKU_Data!D11 -> 129.99 | E11: =SKU_Data!E11 -> 7211 | F11: =H_rate*D11 -> 25.998 | G11: =ROUND(SQRT(2*E11*S_cost/F11),0) -> 167 | H11: =ROUND(Z_service*SKU_Data!F11*SQRT(SKU_Data!G11),0) -> 25 | I11: =ROUND(E11/365*SKU_Data!G11+H11,0) -> 94 | J11: =ROUND(E11/(E11/12)*S_cost+(E11/12)/2*F11,0) -> 8411 | K11: =ROUND(E11/G11*S_cost+G11/2*F11,0) -> 4330 | L11: =J11-K11 -> 4081
B12: =SKU_Data!B12 -> 1004 | C12: =SKU_Data!C12 -> Field & Stream Sportsman 16 Gun Fir | D12: =SKU_Data!D12 -> 399.98 | E12: =SKU_Data!E12 -> 5616 | F12: =H_rate*D12 -> 79.996 | G12: =ROUND(SQRT(2*E12*S_cost/F12),0) -> 84 | H12: =ROUND(Z_service*SKU_Data!F12*SQRT(SKU_Data!G12),0) -> 21 | I12: =ROUND(E12/365*SKU_Data!G12+H12,0) -> 75 | J12: =ROUND(E12/(E12/12)*S_cost+(E12/12)/2*F12,0) -> 19319 | K12: =ROUND(E12/G12*S_cost+G12/2*F12,0) -> 6703 | L12: =J12-K12 -> 12616
B13: =SKU_Data!B13 -> 1073 | C13: =SKU_Data!C13 -> Pelican Sunstream 100 Kayak | D13: =SKU_Data!D13 -> 199.99 | E13: =SKU_Data!E13 -> 5024 | F13: =H_rate*D13 -> 39.998 | G13: =ROUND(SQRT(2*E13*S_cost/F13),0) -> 112 | H13: =ROUND(Z_service*SKU_Data!F13*SQRT(SKU_Data!G13),0) -> 19 | I13: =ROUND(E13/365*SKU_Data!G13+H13,0) -> 67 | J13: =ROUND(E13/(E13/12)*S_cost+(E13/12)/2*F13,0) -> 8973 | K13: =ROUND(E13/G13*S_cost+G13/2*F13,0) -> 4483 | L13: =J13-K13 -> 4490
B14: =SKU_Data!B14 -> 957 | C14: =SKU_Data!C14 -> Diamondback Women's Serene Classic | D14: =SKU_Data!D14 -> 299.98 | E14: =SKU_Data!E14 -> 4450 | F14: =H_rate*D14 -> 59.996 | G14: =ROUND(SQRT(2*E14*S_cost/F14),0) -> 86 | H14: =ROUND(Z_service*SKU_Data!F14*SQRT(SKU_Data!G14),0) -> 17 | I14: =ROUND(E14/365*SKU_Data!G14+H14,0) -> 60 | J14: =ROUND(E14/(E14/12)*S_cost+(E14/12)/2*F14,0) -> 11724 | K14: =ROUND(E14/G14*S_cost+G14/2*F14,0) -> 5167 | L14: =J14-K14 -> 6557
B15: =SKU_Data!B15 -> 977 | C15: =SKU_Data!C15 -> ENO Atlas Hammock Straps | D15: =SKU_Data!D15 -> 29.99 | E15: =SKU_Data!E15 -> 323 | F15: =H_rate*D15 -> 5.998 | G15: =ROUND(SQRT(2*E15*S_cost/F15),0) -> 73 | H15: =ROUND(Z_service*SKU_Data!F15*SQRT(SKU_Data!G15),0) -> 6 | I15: =ROUND(E15/365*SKU_Data!G15+H15,0) -> 9 | J15: =ROUND(E15/(E15/12)*S_cost+(E15/12)/2*F15,0) -> 681 | K15: =ROUND(E15/G15*S_cost+G15/2*F15,0) -> 440 | L15: =J15-K15 -> 241
B17: TOTAL | L17: =SUM(L6:L15) -> 50627

Sheet SPC_Limits
B2: PER-MODE SPC CONTROL LIMITS
B3: Computed offline from full dataset. Update via spc_monitor.py CLI weekly.
B5: Mode | C5: Sample Size | D5: Mean | E5: Sigma | F5: Spec (USL) | G5: Cp | H5: Cpk | I5: X-bar Centerline | J5: UCL X-bar | K5: LCL X-bar | L5: p-bar (Late %) | M5: UCL p | N5: LCL p | O5: Status
B6: Standard Class | C6: 107752 | D6: 4 | E6: 1.417 | F6: 4 | G6: 0.47 | H6: 0.001 | I6: 4 | J6: 5.897 | K6: 2.094 | L6: 0.381 | M6: 0.526 | N6: 0.236 | O6: NOT CAPABLE
B7: First Class | C7: 27814 | D7: 2 | E7: 0 | F7: 1 | G7: UNDEFINED | H7: UNDEFINED | I7: 2 | J7: 2 | K7: 2 | L7: 1 | M7: 1 | N7: 1 | O7: DETERMINISTIC
B8: Second Class | C8: 35216 | D8: 4 | E8: 1.42 | F8: 2 | G8: -0.235 | H8: -0.469 | I8: 4 | J8: 5.89 | K8: 2.091 | L8: 0.767 | M8: 0.893 | N8: 0.64 | O8: CRITICAL OOS
B9: Same Day | C9: 9737 | D9: 0.478 | E9: 0.5 | F9: 0 | G9: -0.319 | H9: -0.319 | I9: 0.478 | J9: 1.149 | K9: 0 | L9: 0.464 | M9: 0.612 | N9: 0.316 | O9: CRITICAL OOS

Sheet Control_Plan
B2: DMAIC CONTROL PLAN
B3: Lock the gains -- one row per process, monitored daily by spc_monitor.py.
B5: Process | C5: CTQ Characteristic | D5: Spec Limits | E5: Method | F5: Sample | G5: Frequency | H5: Cpk | I5: Reaction Plan | J5: Owner | K5: Review Cadence
B6: Order fulfillment - Standard Class | C6: Days_to_ship | D6: 0-4 days | E6: X-bar/R + p-chart | F6: all daily orders | G6: Daily | H6: 0.001 | I6: NOT CAPABLE - variance reduction project; target Cpk >= 1.33 | J6: Logistics Mgr | K6: Weekly
B7: Order fulfillment - First Class | C7: Days_to_ship | D7: 0-1 days | E7: p-chart | F7: all daily orders | G7: Daily | H7: UNDEFINED | I7: PROCESS DESIGN FAILURE - renegotiate SLA or change carrier | J7: Logistics Mgr | K7: Weekly
B8: Order fulfillment - Second Class | C8: Days_to_ship | D8: 0-2 days | E8: X-bar/R + p-chart | F8: all daily orders | G8: Daily | H8: -0.469 | I8: CRITICAL - mean violates spec; root-cause + redesign | J8: Logistics Mgr | K8: Weekly
B9: Order fulfillment - Same Day | C9: Days_to_ship | D9: 0-0 days | E9: p-chart | F9: all daily orders | G9: Daily | H9: -0.319 | I9: CRITICAL - mean violates spec; root-cause + redesign | J9: Logistics Mgr | K9: Weekly
B10: Inventory replenishment - Top 10 SKU | C10: EOQ adherence | D10: EOQ +/- 10% | E10: Cycle counts | F10: all SKUs | G10: Weekly | H10: N/A | I10: Reorder when ROP triggered; flag any deviation | J10: Inventory Mgr | K10: Weekly
B11: Pre-shipment queue | C11: PENDING_PAYMENT % | D11: < 10% | E11: Daily count | F11: all orders | G11: Daily | H11: N/A | I11: If > 15% trip alert -> payment gateway investigation | J11: Ops Director | K11: Daily

Sheet OEE_Grid
B2: OEE DRILL-THROUGH: SHIPPING MODE x MARKET
B3: OEE = Availability x Performance x Quality. Color: green good, red bad.
B5: Mode | C5: Africa | D5: Europe | E5: LATAM | F5: Pacific Asia | G5: USCA
B6: First Class | C6: 0.014854508 | D6: 0.020509872 | E6: 0.025635122 | F6: 0.024025378 | G6: 0.023646071
B7: Same Day | C7: 0 | D7: 0 | E7: 0 | F7: 0 | G7: 0
B8: Second Class | C8: 0.1292183 | D8: 0.13074595 | E8: 0.1400437 | F8: 0.12930357 | G8: 0.13382672
B9: Standard Class | C9: 0.54138133 | D9: 0.54284989 | E9: 0.54382281 | F9: 0.5388253 | G9: 0.54284034

Sheet Summary
B2: EXECUTIVE SUMMARY -- KPIs
B4: DMAIC Phase | C4: KPI | D4: Value | E4: Target | F4: Status
B5: Define | C5: Firm-wide late-delivery rate | D5: 0.548 | E5: 0.05 | F5: CRITICAL
B6: Define | C6: Margin erosion per late order | D6: 0.78 | E6: 0.0 | F6: AMBER
B7: Measure | C7: Standard Class Cpk | D7: 0.001 | E7: 1.33 | F7: NOT CAPABLE
B8: Measure | C8: First Class p (late) | D8: 0.953 | E8: 0.05 | F8: CRITICAL
B9: Measure | C9: Second Class Cpk | D9: -0.469 | E9: 1.33 | F9: OUT OF SPEC
B10: Analyze | C10: PENDING_PAYMENT bottleneck | D10: 0.221 | E10: 0.1 | F10: AMBER
B11: Analyze | C11: BPMN states with > 5% volume | D11: 6 | E11: <= 4 | F11: INFORMATIONAL
B12: Improve | C12: Top-10 SKU EOQ savings ($) | D12: 50629 | E12: N/A | F12: GREEN
B13: Improve | C13: Avg Safety Stock per SKU | D13: 40 | E13: N/A | F13: INFORMATIONAL
B14: Control | C14: Modes with active Control Plan | D14: 4 | E14: 4 | F14: GREEN
B18: Pyramid Recommendation
B19: TOP: Adopt 4-mode Control Plan; redesign First Class SLA from 1d to 2d immediately
B20: SUPPORT 1 (Define/Measure): All 4 modes statistically out-of-control; SPC monitoring is essential
B21: SUPPORT 2 (Analyze): PENDING_PAYMENT queue absorbs 22% of orders -- payment gateway is root cause
B22: SUPPORT 3 (Improve): Top-10 SKU EOQ rollout: ~$50K/yr savings; Safety Stock at 95% service level
B23: SUPPORT 4 (Control): spc_monitor.py CLI runs daily; Western Electric rules trip alerts; weekly review
