Workbook

Sheet Cover
B2: The Capital Structure Audit
B5: Optimizing Leverage in Volatile Markets | EnergyCo + Brent Crude (1987-2022)
B7: Engagement Brief
B8: EnergyCo - a $50B revenue, BBB-rated upstream pure-play - is considering a $2B debt-funded expansion. With Brent crude vol clustering (35yr persistence = 0.9930) and rising rates, leadership needs to know the OPTIMAL CAPITAL STRUCTURE without risking insolvency. This audit anchors all systematic-risk math to the empirical Brent record - 9,011 daily observations spanning 35.5 years.
B10: Anchor
B11: Dataset | C11: Brent Crude Spot Prices (Kaggle / U.S. EIA)
B12: Span | C12: 1987-05-20 to 2022-11-14 (35.5 years, 9,011 obs)
B13: Price range | C13: $9.10 to $143.95 / barrel
B14: Reference firm | C14: EnergyCo: $50B revenue, 28% EBITDA margin, BBB credit, 25% effective tax
B15: Project under review | C15: $2B upstream expansion, 10-yr life, base $400M Y1 EBITDA
B17: Methodology
B18: Stationarity test | C18: ADF on log-returns: stat=-16.43, p<0.0001 (PASSED)
B19: Vol clustering test | C19: ARCH-LM: stat=1299, p<1e-9 (strong clustering)
B20: GARCH model | C20: GARCH(1,1) Student-t innovations (heavy tails confirmed)
B21: Cost of equity | C21: CAPM (single-factor energy) + APT (level + vol) cross-check
B22: Capital structure | C22: MM with taxes + levered beta + distress premium
B23: Real option | C23: Black-Scholes call on project value, sigma from GARCH long-run
B24: Default model | C24: Merton-style 1-year PoD across leverage x vol grid
B26: Hero Findings
B27: Optimal leverage zone is D/V = 30%-40% (WACC ~9.0%, near-zero PoD even in crisis vol). Above 50% D/V, default probability rises non-linearly: <1% at 40%, ~14% at 50%, 63% at 60%, 99%+ at 70%. The Real Option to DELAY the $2B project is worth $281M of time value (vs $400M intrinsic) - because base-case NPV is marginally negative at -$64M, and the GARCH-implied sigma of 46% makes waiting valuable. RECOMMENDATION: target 30-35% D/V (just below current), then re-evaluate the project after a quarter of vol clarity.

Sheet Inputs
B2: Inputs - All Assumptions
B4: 1. Macro / Market
B5: Parameter | C5: Value | D5: Unit | E5: Note
B6: Risk-free rate (10y Treasury) | C6: 0.045 | D6: % | E6: Current proxy
B7: Brent risk premium (35yr) | C7: 0.07 | D7: % | E7: Historical Brent excess return
B8: Brent vol risk premium (RP_vol) | C8: 0.02 | D8: % | E8: APT second factor
B9: Effective corporate tax rate | C9: 0.25 | D9: % | E9: US blended
B11: 2. EnergyCo Financials
B12: Revenue | C12: 50000000000 | D12: $ | E12: $50B - industry median for $50B BBB upstream
B13: EBITDA margin | C13: 0.28 | D13: % | E13: 28% - industry typical
B14: Depreciation (annual) | C14: 3500000000 | D14: $ | E14: ~7% of revenue
B15: Capex (maintenance) | C15: 4000000000 | D15: $ | E15: ~8% of revenue
B16: Pre-tax cost of debt (BBB base) | C16: 0.065 | D16: % | E16: BBB credit spread + risk-free
B17: Equity beta vs Brent | C17: 0.85 | D17: - | E17: Industry-typical for upstream pure-play
B18: Asset vol / Brent vol ratio | C18: 0.55 | D18: - | E18: Firm asset vol = 55% of commodity vol
B19: Firm value (unlevered) | C19: 75000000000 | D19: $ | E19: 1.5x revenue (energy industry EV multiple)
B21: 3. Project Under Review
B22: Capex (Year 0) | C22: 2000000000 | D22: $ | E22: Upfront investment
B23: Year 1 EBITDA | C23: 400000000 | D23: $ | E23: Base case projection
B24: EBITDA decline rate (Y1-Y5) | C24: 0.05 | D24: % | E24: 5%/yr early years
B25: EBITDA decline rate (Y6-Y10) | C25: 0.1 | D25: % | E25: 10%/yr mature years
B26: Terminal salvage value (Y10) | C26: 200000000 | D26: $ | E26: 10% of original capex
B27: PV of project cash flows | C27: 2400000000 | D27: $ | E27: S in Black-Scholes (base case)
B28: Real Option delay horizon | C28: 1 | D28: yrs | E28: T in Black-Scholes
B30: 4. GARCH(1,1) Outputs (locked from notebook)
B31: Persistence (alpha + beta) | C31: 0.993 | D31: - | E31: Vol shocks decay slowly
B32: Half-life of vol shocks | C32: 99.2 | D32: days | E32: Time to half of shock impact
B33: Long-run annualized vol | C33: 0.4583 | D33: % | E33: Used as Black-Scholes sigma
B34: Sample annualized vol | C34: 0.4053 | D34: % | E34: Empirical std × sqrt(252)
B35: Student-t df (nu) | C35: 5.87 | D35: - | E35: Lower = fatter tails
B36: 90-day fwd vol (Day 90) | C36: 0.4164 | D36: % | E36: Forecast endpoint

Sheet GARCH_Outputs
B2: GARCH(1,1) Student-t Output Summary
B4: GARCH(1,1) with Student-t innovations fits Brent's heavy-tailed return distribution. Persistence of 0.9930 means volatility shocks decay slowly (half-life ~99 days). Long-run vol is 45.83% annualized - this is the sigma we use for Black-Scholes.
B6: FIT PARAMETERS
B7: Parameter | C7: Value | D7: Unit | E7: Note
B8: omega | C8: 0.058018 | D8: (%)^2 | E8: Long-run variance constant
B9: alpha[1] | C9: 0.0831 | D9: - | E9: ARCH effect (lagged squared shock)
B10: beta[1] | C10: 0.91 | D10: - | E10: GARCH effect (lagged variance)
B11: Persistence (alpha + beta) | C11: 0.993 | D11: - | E11: <1 required for stationarity
B12: Half-life of vol shocks | C12: 99.2 | D12: days | E12: -ln(2)/ln(persistence)
B13: Long-run vol (annualized) | C13: 0.4583 | D13: % | E13: sqrt(omega/(1-persistence) * 252)
B14: Sample vol (annualized) | C14: 0.4053 | D14: % | E14: Empirical std * sqrt(252)
B15: Student-t df (nu) | C15: 5.87 | D15: - | E15: Lower = fatter tails
B16: Log-likelihood | C16: -19026 | D16: - | E16: GARCH > GARCH-Normal by >1500 LL units
B17: AIC | C17: 38063 | D17: - | E17: Lower better
B18: BIC | C18: 38098 | D18: - | E18: Lower better
B20: VOLATILITY REGIMES (35-year history)
B21: Regime | C21: Lower | D21: Upper | E21: % of History | F21: Description
B22: LOW | C22: 0 | D22: 0.28 | E22: 33% | F22: Calm market - GARCH cond vol < 28%
B23: MEDIUM | C23: 0.28 | D23: 0.37 | E23: 34% | F23: Typical regime - 28-37%
B24: HIGH | C24: 0.37 | D24: 0.6 | E24: 28% | F24: Elevated stress - 37-60%
B25: CRISIS | C25: 0.6 | E25: 5% | F25: Crisis regime - GARCH cond vol > 60%

Sheet CAPM_APT
B2: Cost of Equity - CAPM and APT
B4: Two methods, cross-check. CAPM uses Brent as the single systematic factor (energy CAPM). APT adds Brent volatility as a second factor (negative beta = firm underperforms when vol rises). The two should be close; large gaps would signal model misspecification.
B6: 1. CAPM (Single-Factor Energy Model)
B7: Risk-free rate | C7: =Rf -> 0.045
B8: Beta vs Brent | C8: =Beta_Brent -> 0.85
B9: Brent risk premium | C9: =Brent_RP -> 0.07
B10: Ke (CAPM) = Rf + beta * RP | C10: =C7+C8*C9 -> 0.1045
B12: 2. APT (Two-Factor: Brent Level + Brent Vol)
B13: beta_level (Brent returns) | C13: 0.85
B14: RP_level | C14: =Brent_RP -> 0.07
B15: beta_vol (Brent vol) | C15: -0.15
B16: RP_vol | C16: =RP_vol -> 0.02
B17: Ke (APT) = Rf + b_lev*RP_lev + b_vol*RP_vol | C17: =Rf + C13*C14 + C15*C16 -> 0.1015
B19: CROSS-CHECK
B20: CAPM Ke | C20: =C10 -> 0.1045
B21: APT Ke | C21: =C17 -> 0.1015
B22: Gap (APT - CAPM) | C22: =C21-C20 -> -0.003

Sheet MM_TaxShield
B2: Modigliani-Miller with Taxes - Leverage Scenarios
B4: V_Levered = V_Unlevered + Tc x D. WACC bottoms at the optimal capital structure point. Beyond that, distress premium on debt and rising levered beta push WACC back up. Yellow row = optimal D/V (lowest WACC).
B6: D/V | C6: D/E | D6: Debt ($B) | E6: Tax Shield ($B) | F6: V_Lev ($B) | G6: beta_L | H6: Ke | I6: Kd | J6: WACC | K6: WACC Rank
B7: 0 | C7: =IF(B7<1, B7/(1-B7), 0) -> 0 | D7: =IF(B7<1, V_Unlevered*B7/(1-B7)/1000000000, 0) -> 0 | E7: =Tax_Rate*D7 -> 0 | F7: =V_Unlevered/1000000000+E7 -> 75 | G7: =0.673267326732673*(1+(1-Tax_Rate)*C7) -> 0.67326733 | H7: =Rf+G7*Brent_RP -> 0.092128713 | I7: =Pre_Tax_Cod + IF(B7>0.3, 0.02*(B7/0.5)^2, 0) -> 0.065 | J7: =(1-B7)*H7 + B7*I7*(1-Tax_Rate) -> 0.092128713 | K7: =RANK(J7, $J$7:$J$14, 1) -> 4
B8: 0.1 | C8: =IF(B8<1, B8/(1-B8), 0) -> 0.11111111 | D8: =IF(B8<1, V_Unlevered*B8/(1-B8)/1000000000, 0) -> 8.3333333 | E8: =Tax_Rate*D8 -> 2.0833333 | F8: =V_Unlevered/1000000000+E8 -> 77.083333 | G8: =0.673267326732673*(1+(1-Tax_Rate)*C8) -> 0.72937294 | H8: =Rf+G8*Brent_RP -> 0.096056106 | I8: =Pre_Tax_Cod + IF(B8>0.3, 0.02*(B8/0.5)^2, 0) -> 0.065 | J8: =(1-B8)*H8 + B8*I8*(1-Tax_Rate) -> 0.091325495 | K8: =RANK(J8, $J$7:$J$14, 1) -> 3
B9: 0.2 | C9: =IF(B9<1, B9/(1-B9), 0) -> 0.25 | D9: =IF(B9<1, V_Unlevered*B9/(1-B9)/1000000000, 0) -> 18.75 | E9: =Tax_Rate*D9 -> 4.6875 | F9: =V_Unlevered/1000000000+E9 -> 79.6875 | G9: =0.673267326732673*(1+(1-Tax_Rate)*C9) -> 0.79950495 | H9: =Rf+G9*Brent_RP -> 0.10096535 | I9: =Pre_Tax_Cod + IF(B9>0.3, 0.02*(B9/0.5)^2, 0) -> 0.065 | J9: =(1-B9)*H9 + B9*I9*(1-Tax_Rate) -> 0.090522277 | K9: =RANK(J9, $J$7:$J$14, 1) -> 2
B10: 0.3 | C10: =IF(B10<1, B10/(1-B10), 0) -> 0.42857143 | D10: =IF(B10<1, V_Unlevered*B10/(1-B10)/1000000000, 0) -> 32.142857 | E10: =Tax_Rate*D10 -> 8.0357143 | F10: =V_Unlevered/1000000000+E10 -> 83.035714 | G10: =0.673267326732673*(1+(1-Tax_Rate)*C10) -> 0.88967468 | H10: =Rf+G10*Brent_RP -> 0.10727723 | I10: =Pre_Tax_Cod + IF(B10>0.3, 0.02*(B10/0.5)^2, 0) -> 0.065 | J10: =(1-B10)*H10 + B10*I10*(1-Tax_Rate) -> 0.089719059 | K10: =RANK(J10, $J$7:$J$14, 1) -> 1
B11: 0.4 | C11: =IF(B11<1, B11/(1-B11), 0) -> 0.66666667 | D11: =IF(B11<1, V_Unlevered*B11/(1-B11)/1000000000, 0) -> 50 | E11: =Tax_Rate*D11 -> 12.5 | F11: =V_Unlevered/1000000000+E11 -> 87.5 | G11: =0.673267326732673*(1+(1-Tax_Rate)*C11) -> 1.009901 | H11: =Rf+G11*Brent_RP -> 0.11569307 | I11: =Pre_Tax_Cod + IF(B11>0.3, 0.02*(B11/0.5)^2, 0) -> 0.0778 | J11: =(1-B11)*H11 + B11*I11*(1-Tax_Rate) -> 0.092755842 | K11: =RANK(J11, $J$7:$J$14, 1) -> 5
B12: 0.5 | C12: =IF(B12<1, B12/(1-B12), 0) -> 1 | D12: =IF(B12<1, V_Unlevered*B12/(1-B12)/1000000000, 0) -> 75 | E12: =Tax_Rate*D12 -> 18.75 | F12: =V_Unlevered/1000000000+E12 -> 93.75 | G12: =0.673267326732673*(1+(1-Tax_Rate)*C12) -> 1.1782178 | H12: =Rf+G12*Brent_RP -> 0.12747525 | I12: =Pre_Tax_Cod + IF(B12>0.3, 0.02*(B12/0.5)^2, 0) -> 0.085 | J12: =(1-B12)*H12 + B12*I12*(1-Tax_Rate) -> 0.095612624 | K12: =RANK(J12, $J$7:$J$14, 1) -> 6
B13: 0.6 | C13: =IF(B13<1, B13/(1-B13), 0) -> 1.5 | D13: =IF(B13<1, V_Unlevered*B13/(1-B13)/1000000000, 0) -> 112.5 | E13: =Tax_Rate*D13 -> 28.125 | F13: =V_Unlevered/1000000000+E13 -> 103.125 | G13: =0.673267326732673*(1+(1-Tax_Rate)*C13) -> 1.4306931 | H13: =Rf+G13*Brent_RP -> 0.14514851 | I13: =Pre_Tax_Cod + IF(B13>0.3, 0.02*(B13/0.5)^2, 0) -> 0.0938 | J13: =(1-B13)*H13 + B13*I13*(1-Tax_Rate) -> 0.10026941 | K13: =RANK(J13, $J$7:$J$14, 1) -> 7
B14: 0.7 | C14: =IF(B14<1, B14/(1-B14), 0) -> 2.3333333 | D14: =IF(B14<1, V_Unlevered*B14/(1-B14)/1000000000, 0) -> 175 | E14: =Tax_Rate*D14 -> 43.75 | F14: =V_Unlevered/1000000000+E14 -> 118.75 | G14: =0.673267326732673*(1+(1-Tax_Rate)*C14) -> 1.8514851 | H14: =Rf+G14*Brent_RP -> 0.17460396 | I14: =Pre_Tax_Cod + IF(B14>0.3, 0.02*(B14/0.5)^2, 0) -> 0.1042 | J14: =(1-B14)*H14 + B14*I14*(1-Tax_Rate) -> 0.10708619 | K14: =RANK(J14, $J$7:$J$14, 1) -> 8
B16: OPTIMAL CAPITAL STRUCTURE
B17: Optimal D/V | C17: =INDEX(B7:B14, MATCH(1, K7:K14, 0)) -> 0.3
B18: WACC at optimum | C18: =INDEX(J7:J14, MATCH(1, K7:K14, 0)) -> 0.089719059
B19: Tax shield at optimum ($B) | C19: =INDEX(E7:E14, MATCH(1, K7:K14, 0)) -> 8.0357143

Sheet RealOption_BS
B2: Black-Scholes - Real Option to Delay
B4: Should EnergyCo invest the $2B NOW or wait? Treat the investment as a CALL OPTION on project value. Sigma calibrated to Brent GARCH long-run vol (45.83%). The TIME VALUE is the optionality premium - the value of waiting for vol to clarify.
B6: INPUTS
B7: S = PV of project cash flows ($) | C7: =Project_S -> 2400000000
B8: K = Project cost ($) | C8: =Project_Capex -> 2000000000
B9: T = Delay horizon (years) | C9: =Option_T -> 1
B10: r = Risk-free rate | C10: =Rf -> 0.045
B11: sigma = Brent GARCH long-run vol | C11: =GARCH_LongRunVol -> 0.4583
B13: BLACK-SCHOLES COMPUTATION
B14: d1 = (ln(S/K) + (r + 0.5σ²)T) / (σ√T) | C14: =(LN(C7/C8) + (C10 + 0.5*C11^2)*C9) / (C11*SQRT(C9)) -> 0.72516038
B15: d2 = d1 - σ√T | C15: =C14 - C11*SQRT(C9) -> 0.26686038
B16: N(d1) | C16: =NORMSDIST(C14) -> 0.76582318
B17: N(d2) | C17: =NORMSDIST(C15) -> 0.60521167
B19: OUTPUTS
B20: Real Option Value (Call) | C20: =C7*C16 - C8*EXP(-C10*C9)*C17 -> 6.8081396e+08
B21: Intrinsic Value (S - K) | C21: =C7-C8 -> 400000000
B22: Time Value (Optionality premium) | C22: =C20-C21 -> 2.8081396e+08
B23: Optionality % above intrinsic | C23: =C22/C21 -> 0.70203491

Sheet CF_Forecast
B2: 10-Year Project Cash Flow Forecast (Indirect Method)
B4: Indirect Method: NOPAT + D&A - Capex - dWC. EBITDA declines 5%/yr in years 1-5, 10%/yr in 6-10. Year 0 is initial $2B capex. Year 10 includes $200M salvage.
B6: Line item | C6: Y0 | D6: Y1 | E6: Y2 | F6: Y3 | G6: Y4 | H6: Y5 | I6: Y6 | J6: Y7 | K6: Y8 | L6: Y9 | M6: Y10
B7: EBITDA | C7: 0 | D7: =Inputs!$C$23 -> 400000000 | E7: =D7*(1-Inputs!$C$24) -> 380000000 | F7: =E7*(1-Inputs!$C$24) -> 361000000 | G7: =F7*(1-Inputs!$C$24) -> 342950000 | H7: =G7*(1-Inputs!$C$24) -> 325802500 | I7: =H7*(1-Inputs!$C$25) -> 293222250 | J7: =I7*(1-Inputs!$C$25) -> 263900025 | K7: =J7*(1-Inputs!$C$25) -> 2.3751002e+08 | L7: =K7*(1-Inputs!$C$25) -> 2.1375902e+08 | M7: =L7*(1-Inputs!$C$25) -> 1.9238312e+08
B8: (-) D&A | C8: 0 | D8: =Project_Capex*0.1 -> 200000000 | E8: =Project_Capex*0.1 -> 200000000 | F8: =Project_Capex*0.1 -> 200000000 | G8: =Project_Capex*0.1 -> 200000000 | H8: =Project_Capex*0.1 -> 200000000 | I8: =Project_Capex*0.1 -> 200000000 | J8: =Project_Capex*0.1 -> 200000000 | K8: =Project_Capex*0.1 -> 200000000 | ... M8: =Project_Capex*0.1 -> 200000000
B9: EBIT | C9: 0 | D9: =D7-D8 -> 200000000 | E9: =E7-E8 -> 180000000 | F9: =F7-F8 -> 161000000 | G9: =G7-G8 -> 142950000 | H9: =H7-H8 -> 125802500 | I9: =I7-I8 -> 93222250 | J9: =J7-J8 -> 63900025 | K9: =K7-K8 -> 37510022 | ... M9: =M7-M8 -> -7616881.8
B10: (-) Tax | C10: 0 | D10: =MAX(D9*Tax_Rate, 0) -> 50000000 | E10: =MAX(E9*Tax_Rate, 0) -> 45000000 | F10: =MAX(F9*Tax_Rate, 0) -> 40250000 | G10: =MAX(G9*Tax_Rate, 0) -> 35737500 | H10: =MAX(H9*Tax_Rate, 0) -> 31450625 | I10: =MAX(I9*Tax_Rate, 0) -> 23305562 | J10: =MAX(J9*Tax_Rate, 0) -> 15975006 | K10: =MAX(K9*Tax_Rate, 0) -> 9377505.6 | ... M10: =MAX(M9*Tax_Rate, 0) -> 0
B11: NOPAT | C11: 0 | D11: =D9-D10 -> 150000000 | E11: =E9-E10 -> 135000000 | F11: =F9-F10 -> 120750000 | G11: =G9-G10 -> 107212500 | H11: =H9-H10 -> 94351875 | I11: =I9-I10 -> 69916688 | J11: =J9-J10 -> 47925019 | K11: =K9-K10 -> 28132517 | ... M11: =M9-M10 -> -7616881.8
B12: (+) D&A back | C12: 0 | D12: =D8 -> 200000000 | E12: =E8 -> 200000000 | F12: =F8 -> 200000000 | G12: =G8 -> 200000000 | H12: =H8 -> 200000000 | I12: =I8 -> 200000000 | J12: =J8 -> 200000000 | K12: =K8 -> 200000000 | ... M12: =M8 -> 200000000
B13: (-) Capex | C13: =-Project_Capex -> -2000000000 | D13: 0 | E13: 0 | F13: 0 | G13: 0 | H13: 0 | I13: 0 | J13: 0 | K13: 0 | L13: 0 | M13: 0
B14: (+) Salvage value | C14: 0 | D14: 0 | E14: 0 | F14: 0 | G14: 0 | H14: 0 | I14: 0 | J14: 0 | K14: 0 | L14: 0 | M14: =Inputs!$C$26 -> 200000000
B15: Free Cash Flow | C15: =C13 -> -2000000000 | D15: =D11+D12+D13+D14 -> 350000000 | E15: =E11+E12+E13+E14 -> 335000000 | F15: =F11+F12+F13+F14 -> 320750000 | G15: =G11+G12+G13+G14 -> 307212500 | H15: =H11+H12+H13+H14 -> 294351875 | I15: =I11+I12+I13+I14 -> 2.6991669e+08 | J15: =J11+J12+J13+J14 -> 2.4792502e+08 | K15: =K11+K12+K13+K14 -> 2.2813252e+08 | ... M15: =M11+M12+M13+M14 -> 3.9238312e+08
B17: Discount factor (at Optimal WACC) | C17: =1/((1+Optimal_WACC)^0) -> 1 | D17: =1/((1+Optimal_WACC)^1) -> 0.91766772 | E17: =1/((1+Optimal_WACC)^2) -> 0.84211404 | F17: =1/((1+Optimal_WACC)^3) -> 0.77278086 | G17: =1/((1+Optimal_WACC)^4) -> 0.70915605 | H17: =1/((1+Optimal_WACC)^5) -> 0.65076961 | I17: =1/((1+Optimal_WACC)^6) -> 0.59719026 | J17: =1/((1+Optimal_WACC)^7) -> 0.54802223 | K17: =1/((1+Optimal_WACC)^8) -> 0.5029023 | L17: =1/((1+Optimal_WACC)^9) -> 0.46149721 | M17: =1/((1+Optimal_WACC)^10) -> 0.42350109
B18: Discounted FCF | C18: =C15*C17 -> -2000000000 | D18: =D15*D17 -> 3.211837e+08 | E18: =E15*E17 -> 2.821082e+08 | F18: =F15*F17 -> 2.4786946e+08 | G18: =G15*G17 -> 2.178616e+08 | H18: =H15*H17 -> 1.9155526e+08 | I18: =I15*I17 -> 1.6119162e+08 | J18: =J15*J17 -> 1.3586842e+08 | ... M18: =M15*M17 -> 1.6617468e+08
B20: NPV @ OPTIMAL WACC
B21: Sum of discounted FCF | C21: =SUM(C18:M18) -> -64396938
B22: WACC used | C22: =Optimal_WACC -> 0.089719059

Sheet NPV_2Way
B2: NPV 2-Way Sensitivity (Brent Scenario x WACC)
B4: Bear ($40 oil) reduces project EBITDA by 40%; Bull ($110) lifts by 40%. WACC varies across the cost-of-capital landscape. NPV = sum of discounted FCFs scaled by Brent multiplier. Green = positive NPV, Red = destroys value.
B6: Brent scenario | C6: 0.07 | D6: 0.08 | E6: 0.09 | F6: 0.1 | G6: 0.11 | H6: 0.12
B7: Bear ($40) | C7: -8.1501321e+08 | D7: -8.6536456e+08 | E7: -9.1237618e+08 | F7: -9.5632472e+08 | G7: -9.9746032e+08 | H7: -1.0360094e+09
B8: Base ($75) | C8: -25022009 | D8: -1.0894093e+08 | E8: -1.8729363e+08 | F8: -2.6054121e+08 | G8: -3.2910054e+08 | H8: -3.9334906e+08
B9: Bull ($110) | C9: 7.6496919e+08 | D9: 6.474827e+08 | E9: 5.3778891e+08 | F9: 4.3524231e+08 | G9: 3.3925925e+08 | H9: 2.4931132e+08
B11: DECISION RULE
B12: Project is value-destructive in Bear scenario at all WACC levels. Base case is marginally negative at optimal WACC. Bull case is highly positive. The asymmetry + Brent's 46% volatility justifies WAITING (Real Option to Delay = $281M time value).

Sheet Risk_Heatmap
B2: Merton-Style Probability of Default - Risk Heatmap
B4: PoD = N(-DD), where DD = (ln(V/D) + (mu - 0.5σ²)T) / (σ√T). Asset volatility = 55% of Brent vol (industry typical for upstream). 1-year horizon. Color: green < 1%, amber 1-15%, red > 15%.
B6: D/V Leverage | C6: LOW (25%) | D6: MEDIUM (40%) | E6: HIGH (60%) | F6: CRISIS (80%)
B7: 0.2 | C7: 3.1211129e-27 | D7: 1.4782375e-11 | E7: 7.097757e-06 | F7: 0.00079057664
B8: 0.3 | C8: 5.2205665e-13 | D8: 5.7774637e-06 | E8: 0.0023113464 | F8: 0.021284699
B9: 0.4 | C9: 8.8498752e-06 | D9: 0.0044545029 | E9: 0.049265488 | F9: 0.12656847
B10: 0.5 | C10: 0.032517221 | D10: 0.13871582 | E10: 0.26356123 | F10: 0.35269542
B11: 0.6 | C11: 0.65933574 | D11: 0.6269129 | E11: 0.62075288 | F11: 0.62810708
B12: 0.7 | C12: 0.99531095 | D12: 0.95455795 | E12: 0.88854658 | F12: 0.84384246
B14: RECOMMENDED LEVERAGE BAND
B15: D/V = 30%-40% captures most of the tax shield benefit while staying well below the PoD cliff (which begins at 50% D/V in median vol regimes). Above 60% D/V, PoD exceeds 60% even in calm regimes - effectively non-investable.

Sheet Scenarios
B2: Capital Structure Scenarios
B4: 3 capital structure scenarios + active picker. Switch between Conservative (D/V=20%), Recommended (30%), and Aggressive (50%). Watch how PoD, WACC, and tax shield change.
B6: Lever | C6: Conservative | D6: Recommended | E6: Aggressive
B7: D/V leverage | C7: 0.2 | D7: 0.3 | E7: 0.5
B8: WACC (from MM) | C8: =VLOOKUP(C7, MM_TaxShield!$B$7:$J$14, 9, FALSE()) -> 0.090522277 | D8: =VLOOKUP(D7, MM_TaxShield!$B$7:$J$14, 9, FALSE()) -> 0.089719059 | E8: =VLOOKUP(E7, MM_TaxShield!$B$7:$J$14, 9, FALSE()) -> 0.095612624
B9: Tax shield ($B) | C9: =VLOOKUP(C7, MM_TaxShield!$B$7:$J$14, 4, FALSE()) -> 4.6875 | D9: =VLOOKUP(D7, MM_TaxShield!$B$7:$J$14, 4, FALSE()) -> 8.0357143 | E9: =VLOOKUP(E7, MM_TaxShield!$B$7:$J$14, 4, FALSE()) -> 18.75
B10: PoD at MEDIUM vol regime | C10: =VLOOKUP(C7, Risk_Heatmap!$B$7:$F$12, 3, FALSE()) -> 1.4782375e-11 | D10: =VLOOKUP(D7, Risk_Heatmap!$B$7:$F$12, 3, FALSE()) -> 5.7774637e-06 | E10: =VLOOKUP(E7, Risk_Heatmap!$B$7:$F$12, 3, FALSE()) -> 0.13871582
B12: ACTIVE SCENARIO: | C12: 2 | D12: (1=Conservative, 2=Recommended, 3=Aggressive)
B13: Active D/V | C13: =INDEX(C7:E7, $C$12) -> 0.3
B14: Active WACC | C14: =INDEX(C8:E8, $C$12) -> 0.089719059
B15: Active Tax Shield ($B) | C15: =INDEX(C9:E9, $C$12) -> 8.0357143
B16: Active PoD (MEDIUM vol) | C16: =INDEX(C10:E10, $C$12) -> 5.7774637e-06

Sheet Summary
B2: Executive Summary
B4: HERO NUMBERS
B5: GARCH persistence | C5: 0.9930
B6: GARCH half-life (vol shocks) | C6: 99.2 days
B7: GARCH long-run vol (annualized) | C7: 45.83%
B8: CAPM cost of equity | C8: 10.45%
B9: APT cost of equity | C9: 10.15%
B10: Optimal D/V leverage | C10: 30%
B11: WACC at optimum | C11: 8.97%
B12: Tax shield value at optimum | C12: $8.04 B
B13: Real Option value (delay) | C13: $681 M
B14: Real Option time value | C14: $281 M | D14: value of waiting
B15: Project NPV at base WACC | C15: ($64 M) | D15: marginally negative
B16: Project IRR (base case) | C16: 8.20%
B17: PoD at D/V=40%, MED vol | C17: 0.45% | D17: low
B18: PoD at D/V=60%, MED vol | C18: 62.69% | D18: non-investable
B20: RECOMMENDATION (PYRAMID PRINCIPLE)
B21: Top of pyramid | C21: Adopt D/V = 30%-35% as optimal capital structure. Defer the $2B project by ~6 months to capture the $281M time value and re-evaluate after vol clarifies. Current D/V (~26%) is already near-optimal; the project itself is the bigger decision.
B22: Supporting #1 (PRICING) | C22: Cost of equity converges between CAPM (10.45%) and APT (10.15%). The 30bp gap reflects EnergyCo's negative beta on Brent vol. WACC bottoms at 8.97% at D/V=30%.
B23: Supporting #2 (CAPITAL STRUCTURE) | C23: MM tax shield benefit is $2.08B at D/V=10%, rising to $8.04B at D/V=30%. Beyond D/V=30%, distress premium on debt (kicks in above D/V=30%) and rising levered beta push WACC back up. Tax shield gains are dwarfed by financing-cost increases above D/V=40%.
B24: Supporting #3 (RISK) | C24: Merton PoD non-linearity: <1% at D/V=40% even in CRISIS vol; jumps to 14% at D/V=50%, 63% at D/V=60%. The 'cliff' between 50%-60% is sharp - no leverage above 50% is defensible for a BBB-rated firm with this commodity exposure.
B25: Supporting #4 (REAL OPTION) | C25: Brent's 45.83% long-run vol gives the option to delay $281M of time value above the $400M intrinsic NPV. The decision-rule: invest immediately UNLESS competitive pressure or time-decay exceeds ~$23M/month.
