Workbook

Sheet Cover
B2: Workforce Risk Audit
B5: Attrition, Compensation & Retention Strategy | IBM HR Analytics anchor
B7: Engagement Brief
B8: IBM's HR analytics team is preparing a board-level briefing on workforce attrition. The CHRO needs to know which segments are bleeding talent, what's causing exits, what the 3-year cost trajectory is under different macro scenarios, and where to invest retention dollars first. This workbook computes the answer in formulas; the Tableau dashboard makes it interactive; the Pyramid deck delivers the recommendation.
B10: Anchor
B11: Dataset | C11: IBM HR Analytics Employee Attrition (Kaggle)
B12: Population | C12: 1,470 employees, 3 departments, 9 job roles, 5 job levels
B13: Overall attrition | C13: 16.12%
B14: Worst role | C14: Sales Representative — 39.8% attrition
B15: Best role | C15: Research Director — 2.5% attrition
B16: Logistic regression AUC | C16: 0.748 (out-of-sample holdout)
B18: Methodology
B19: Compensation DuPont | C19: Cost-per-Retained-FTE = Pay × (1/Retention) × (1/TenureMult)
B20: Causation analysis | C20: Logistic regression with multicollinearity check (VIF) and standardised coefficients
B21: Cost forecast | C21: Departures × Salary × Replacement multiplier (1.5×) compounded with wage inflation
B22: 3 scenarios | C22: Baseline / Wage-Inflation / Retention-Investment
B23: Sensitivity grid | C23: 2-way data table: cost vs (Wage Inflation × Replacement Multiplier)
B25: How to use this workbook
B26: 1. Inputs | C26: Edit BLUE cells - macro assumptions, replacement multiplier
B27: 2. Scenarios | C27: Toggle Active Scenario (1/2/3); whole model recalculates
B28: 3. Cost_Forecast | C28: 4-year projection per scenario; pulls from Inputs and Headcount
B29: 4. Sensitivity | C29: Stress-test cost against macro inputs
B30: 5. Summary | C30: Cumulative cost comparison; recommendation
B32: Color coding
B33: BLUE TEXT | C33: Hardcoded inputs - editable
B34: BLACK TEXT | C34: Formulas - do not overwrite
B35: GREEN TEXT | C35: Cross-sheet links
B36: YELLOW BG | C36: Critical assumptions - edit first when stress-testing

Sheet Headcount
B2: Workforce Composition - by Job Level
B4: JobLevel 1 is the bleeding wound: 26.3% attrition, lowest pay, shortest tenure. JobLevel 4-5 are stable. The retention strategy is targeted at JobLevel 1.
B6: JobLevel | C6: Headcount | D6: Attrition Rate | E6: Annual Salary (median) | F6: Median Tenure (yrs) | G6: Annual Departures | H6: Replace Cost ($1.5x)
B7: 1 | C7: 543 | D7: 0.2634 | E7: 32040 | F7: 3 | G7: =C7*D7 -> 143.0262
B8: 2 | C8: 534 | D8: 0.0974 | E8: 64080 | F8: 6 | G8: =C8*D8 -> 52.0116
B9: 3 | C9: 218 | D9: 0.1468 | E9: 119760 | F9: 9 | G9: =C9*D9 -> 32.0024
B10: 4 | C10: 106 | D10: 0.0472 | E10: 193848 | F10: 12.5 | G10: =C10*D10 -> 5.0032
B11: 5 | C11: 69 | D11: 0.0725 | E11: 230784 | F11: 18 | G11: =C11*D11 -> 5.0025
B12: TOTAL | C12: =SUM(C7:C11) -> 1470 | D12: =SUMPRODUCT(C7:C11,D7:D11)/SUM(C7:C11) -> 0.16125571 | G12: =SUM(G7:G11) -> 237.0459

Sheet DuPont
B2: Compensation DuPont - Cost per Retained FTE
B4: Cost-per-Retained-FTE = Annual Pay × (1/Retention Rate) × (1/Tenure Multiplier). This deconstructs which retention lever matters most: pay, retention rate, or tenure productivity.
B6: JobRole | C6: Headcount | D6: Pay Annual | E6: Retention Rate | F6: 1/Retention | G6: Median Tenure | H6: Tenure Mult | I6: Cost per Retained | J6: vs Baseline ($60k)
B7: Sales Representative | C7: 83 | D7: 30948 | E7: 0.6024 | F7: =1/E7 -> 1.6600266 | G7: 2 | H7: =G7/5 -> 0.4 | I7: =D7*F7/H7 -> 128436.25 | J7: =I7/60000 -> 2.1406042
B8: Research Director | C8: 80 | D8: 198120 | E8: 0.975 | F8: =1/E8 -> 1.025641 | G8: 9 | H8: =G8/5 -> 1.8 | I8: =D8*F8/H8 -> 112888.89 | J8: =I8/60000 -> 1.8814815
B9: Manager | C9: 102 | D9: 209454 | E9: 0.951 | F9: =1/E9 -> 1.0515247 | G9: 12.5 | H9: =G9/5 -> 2.5 | I9: =D9*F9/H9 -> 88098.423 | J9: =I9/60000 -> 1.468307
B10: Sales Executive | C10: 326 | D10: 74772 | E10: 0.8252 | F10: =1/E10 -> 1.2118274 | G10: 7 | H10: =G10/5 -> 1.4 | I10: =D10*F10/H10 -> 64721.972 | J10: =I10/60000 -> 1.0786995
B11: Healthcare Representative | C11: 131 | D11: 81732 | E11: 0.9313 | F11: =1/E11 -> 1.0737679 | G11: 7 | H11: =G11/5 -> 1.4 | I11: =D11*F11/H11 -> 62686.567 | J11: =I11/60000 -> 1.0447761
B12: Manufacturing Director | C12: 145 | D12: 77364 | E12: 0.931 | F12: =1/E12 -> 1.0741139 | G12: 7 | H12: =G12/5 -> 1.4 | I12: =D12*F12/H12 -> 59355.532 | J12: =I12/60000 -> 0.98925886
B13: Laboratory Technician | C13: 259 | D13: 34632 | E13: 0.7606 | F13: =1/E13 -> 1.3147515 | G13: 4 | H13: =G13/5 -> 0.8 | I13: =D13*F13/H13 -> 56915.593 | J13: =I13/60000 -> 0.94859322
B14: Human Resources | C14: 52 | D14: 37116 | E14: 0.7692 | F14: =1/E14 -> 1.300052 | G14: 5 | H14: =G14/5 -> 1 | I14: =D14*F14/H14 -> 48252.73 | J14: =I14/60000 -> 0.80421217
B15: Research Scientist | C15: 292 | D15: 34650 | E15: 0.839 | F15: =1/E15 -> 1.1918951 | G15: 4.5 | H15: =G15/5 -> 0.9 | I15: =D15*F15/H15 -> 45887.962 | J15: =I15/60000 -> 0.76479936

Sheet Inputs
B2: Macro Inputs & Cost Parameters
B4: 1. Macro Assumptions
B5: Parameter | C5: Value | D5: Unit | E5: Note
B6: Wage inflation - Baseline | C6: 0.04 | D6: %/yr | E6: US wage-growth proxy, long-term avg
B7: Wage inflation - High Inflation | C7: 0.07 | D7: %/yr | E7: Stress scenario: tight labour market
B8: Replacement cost multiplier | C8: 1.5 | D8: x | E8: Industry rule of thumb; 1.5x annual salary
B9: Retention investment / FTE | C9: 5000 | D9: $/yr | E9: Spend per JobLevel-1 employee
B10: Target attrition (JL-1) | C10: 0.15 | D10: % | E10: Achievable with retention program
B11: Attrition rise under inflation | C11: 0.02 | D11: pp | E11: +2pp company-wide if wages lag market

Sheet Scenarios
B2: Scenario Definitions
B4: Parameter | C4: Baseline | D4: Wage-Inflation | E4: Retention-Investment
B5: Wage inflation | C5: =WageInfl_Base -> 0.04 | D5: =WageInfl_High -> 0.07 | E5: =WageInfl_Base -> 0.04
B6: Attrition shift (pp) | C6: 0 | D6: =Attr_Rise_Infl -> 0.02 | E6: 0
B7: JL-1 attrition rate | C7: =VLOOKUP(1,Headcount!B7:D11,3,FALSE()) -> 0.2634 | D7: =VLOOKUP(1,Headcount!B7:D11,3,FALSE())+Attr_Rise_Infl -> 0.2834 | E7: =Target_Attr_L1 -> 0.15
B8: Retention spend / FTE / yr | C8: 0 | D8: 0 | E8: =Retention_Invest -> 5000
B10: ACTIVE SCENARIO: | C10: 1 | D10: (1=Baseline, 2=Wage-Infl, 3=Retention-Invest)
B11: Active wage inflation | C11: =INDEX(C5:E5, $C$10) -> 0.04
B12: Active attrition shift | C12: =INDEX(C6:E6, $C$10) -> 0
B13: Active JL-1 attrition | C13: =INDEX(C7:E7, $C$10) -> 0.2634
B14: Active retention spend | C14: =INDEX(C8:E8, $C$10) -> 0

Sheet Cost_Forecast
B2: 4-Year Attrition Cost Forecast - Active Scenario
B4: Year-by-year forecast for the active scenario. Edit the Scenario picker (Scenarios sheet, cell C10) to recompute. Year 0 = today; through Year 3.
B6: JobLevel | C6: Headcount | D6: Attr Rate | E6: Salary Y0 | F6: Y0 Cost | G6: Y1 Cost | H6: Y2 Cost | I6: Y3 Cost | J6: 4yr Cumulative
B7: 1 | C7: =Headcount!C7 -> 543 | D7: =Active_JL1_Attr -> 0.2634 | E7: =Headcount!E7 -> 32040 | F7: =C7*D7*E7*Replace_Mult -> 6873839.2 | G7: =C7*D7*E7*(1+Active_WageInfl)^1*Replace_Mult -> 7148792.7 | H7: =C7*D7*E7*(1+Active_WageInfl)^2*Replace_Mult -> 7434744.4 | I7: =C7*D7*E7*(1+Active_WageInfl)^3*Replace_Mult -> 7732134.2 | J7: =SUM(F7:I7) -> 29189511
B8: 2 | C8: =Headcount!C8 -> 534 | D8: =Headcount!D8+Active_AttrShift -> 0.0974 | E8: =Headcount!E8 -> 64080 | F8: =C8*D8*E8*Replace_Mult -> 4999355 | G8: =C8*D8*E8*(1+Active_WageInfl)^1*Replace_Mult -> 5199329.2 | H8: =C8*D8*E8*(1+Active_WageInfl)^2*Replace_Mult -> 5407302.4 | I8: =C8*D8*E8*(1+Active_WageInfl)^3*Replace_Mult -> 5623594.5 | J8: =SUM(F8:I8) -> 21229581
B9: 3 | C9: =Headcount!C9 -> 218 | D9: =Headcount!D9+Active_AttrShift -> 0.1468 | E9: =Headcount!E9 -> 119760 | F9: =C9*D9*E9*Replace_Mult -> 5748911.1 | G9: =C9*D9*E9*(1+Active_WageInfl)^1*Replace_Mult -> 5978867.6 | H9: =C9*D9*E9*(1+Active_WageInfl)^2*Replace_Mult -> 6218022.3 | I9: =C9*D9*E9*(1+Active_WageInfl)^3*Replace_Mult -> 6466743.2 | J9: =SUM(F9:I9) -> 24412544
B10: 4 | C10: =Headcount!C10 -> 106 | D10: =Headcount!D10+Active_AttrShift -> 0.0472 | E10: =Headcount!E10 -> 193848 | F10: =C10*D10*E10*Replace_Mult -> 1454790.5 | G10: =C10*D10*E10*(1+Active_WageInfl)^1*Replace_Mult -> 1512982.1 | H10: =C10*D10*E10*(1+Active_WageInfl)^2*Replace_Mult -> 1573501.4 | I10: =C10*D10*E10*(1+Active_WageInfl)^3*Replace_Mult -> 1636441.4 | J10: =SUM(F10:I10) -> 6177715.4
B11: 5 | C11: =Headcount!C11 -> 69 | D11: =Headcount!D11+Active_AttrShift -> 0.0725 | E11: =Headcount!E11 -> 230784 | F11: =C11*D11*E11*Replace_Mult -> 1731745.4 | G11: =C11*D11*E11*(1+Active_WageInfl)^1*Replace_Mult -> 1801015.3 | H11: =C11*D11*E11*(1+Active_WageInfl)^2*Replace_Mult -> 1873055.9 | I11: =C11*D11*E11*(1+Active_WageInfl)^3*Replace_Mult -> 1947978.1 | J11: =SUM(F11:I11) -> 7353794.7
B12: REPLACEMENT COST TOTAL | C12: =SUM(C7:C11) -> 1470 | F12: =SUM(F7:F11) -> 20808641 | G12: =SUM(G7:G11) -> 21640987 | H12: =SUM(H7:H11) -> 22506626 | I12: =SUM(I7:I11) -> 23406891 | J12: =SUM(J7:J11) -> 88363146
B13: Retention spend (JL-1) | F13: =C7*Active_Retention -> 0 | G13: =C7*Active_Retention -> 0 | H13: =C7*Active_Retention -> 0 | I13: =C7*Active_Retention -> 0 | J13: =SUM(F13:I13) -> 0
B14: GRAND TOTAL (incl retention) | F14: =F12+F13 -> 20808641 | G14: =G12+G13 -> 21640987 | H14: =H12+H13 -> 22506626 | I14: =I12+I13 -> 23406891 | J14: =J12+J13 -> 88363146

Sheet Sensitivity
B2: Sensitivity - Year-3 Cost by Wage Inflation × Replacement Multiplier
B4: How does Year-3 attrition cost change as wage inflation and replacement multiplier shift? Both axes assume Baseline scenario (no retention investment) so this isolates the macro risk.
B6: Replace Mult v | Wage Infl > | C6: 0.02 | D6: 0.03 | E6: 0.04 | F6: 0.05 | G6: 0.06 | H6: 0.07 | I6: 0.08 | J6: 0.09
B7: 1 | C7: =SUMPRODUCT(Headcounts, AttrRates, AnnualSalaries) * (1+C$6)^3 * $B7 -> 14721531 | D7: =SUMPRODUCT(Headcounts, AttrRates, AnnualSalaries) * (1+D$6)^3 * $B7 -> 15158776 | E7: =SUMPRODUCT(Headcounts, AttrRates, AnnualSalaries) * (1+E$6)^3 * $B7 -> 15604594 | F7: =SUMPRODUCT(Headcounts, AttrRates, AnnualSalaries) * (1+F$6)^3 * $B7 -> 16059069 | G7: =SUMPRODUCT(Headcounts, AttrRates, AnnualSalaries) * (1+G$6)^3 * $B7 -> 16522283 | H7: =SUMPRODUCT(Headcounts, AttrRates, AnnualSalaries) * (1+H$6)^3 * $B7 -> 16994320 | I7: =SUMPRODUCT(Headcounts, AttrRates, AnnualSalaries) * (1+I$6)^3 * $B7 -> 17475263 | J7: =SUMPRODUCT(Headcounts, AttrRates, AnnualSalaries) * (1+J$6)^3 * $B7 -> 17965196
B8: 1.25 | C8: =SUMPRODUCT(Headcounts, AttrRates, AnnualSalaries) * (1+C$6)^3 * $B8 -> 18401914 | D8: =SUMPRODUCT(Headcounts, AttrRates, AnnualSalaries) * (1+D$6)^3 * $B8 -> 18948470 | E8: =SUMPRODUCT(Headcounts, AttrRates, AnnualSalaries) * (1+E$6)^3 * $B8 -> 19505743 | F8: =SUMPRODUCT(Headcounts, AttrRates, AnnualSalaries) * (1+F$6)^3 * $B8 -> 20073836 | G8: =SUMPRODUCT(Headcounts, AttrRates, AnnualSalaries) * (1+G$6)^3 * $B8 -> 20652854 | H8: =SUMPRODUCT(Headcounts, AttrRates, AnnualSalaries) * (1+H$6)^3 * $B8 -> 21242900 | I8: =SUMPRODUCT(Headcounts, AttrRates, AnnualSalaries) * (1+I$6)^3 * $B8 -> 21844079 | J8: =SUMPRODUCT(Headcounts, AttrRates, AnnualSalaries) * (1+J$6)^3 * $B8 -> 22456495
B9: 1.5 | C9: =SUMPRODUCT(Headcounts, AttrRates, AnnualSalaries) * (1+C$6)^3 * $B9 -> 22082297 | D9: =SUMPRODUCT(Headcounts, AttrRates, AnnualSalaries) * (1+D$6)^3 * $B9 -> 22738164 | E9: =SUMPRODUCT(Headcounts, AttrRates, AnnualSalaries) * (1+E$6)^3 * $B9 -> 23406891 | F9: =SUMPRODUCT(Headcounts, AttrRates, AnnualSalaries) * (1+F$6)^3 * $B9 -> 24088603 | G9: =SUMPRODUCT(Headcounts, AttrRates, AnnualSalaries) * (1+G$6)^3 * $B9 -> 24783425 | H9: =SUMPRODUCT(Headcounts, AttrRates, AnnualSalaries) * (1+H$6)^3 * $B9 -> 25491480 | I9: =SUMPRODUCT(Headcounts, AttrRates, AnnualSalaries) * (1+I$6)^3 * $B9 -> 26212895 | J9: =SUMPRODUCT(Headcounts, AttrRates, AnnualSalaries) * (1+J$6)^3 * $B9 -> 26947794
B10: 1.75 | C10: =SUMPRODUCT(Headcounts, AttrRates, AnnualSalaries) * (1+C$6)^3 * $B10 -> 25762679 | D10: =SUMPRODUCT(Headcounts, AttrRates, AnnualSalaries) * (1+D$6)^3 * $B10 -> 26527858 | E10: =SUMPRODUCT(Headcounts, AttrRates, AnnualSalaries) * (1+E$6)^3 * $B10 -> 27308040 | F10: =SUMPRODUCT(Headcounts, AttrRates, AnnualSalaries) * (1+F$6)^3 * $B10 -> 28103370 | G10: =SUMPRODUCT(Headcounts, AttrRates, AnnualSalaries) * (1+G$6)^3 * $B10 -> 28913995 | H10: =SUMPRODUCT(Headcounts, AttrRates, AnnualSalaries) * (1+H$6)^3 * $B10 -> 29740060 | I10: =SUMPRODUCT(Headcounts, AttrRates, AnnualSalaries) * (1+I$6)^3 * $B10 -> 30581711 | J10: =SUMPRODUCT(Headcounts, AttrRates, AnnualSalaries) * (1+J$6)^3 * $B10 -> 31439093
B11: 2 | C11: =SUMPRODUCT(Headcounts, AttrRates, AnnualSalaries) * (1+C$6)^3 * $B11 -> 29443062 | D11: =SUMPRODUCT(Headcounts, AttrRates, AnnualSalaries) * (1+D$6)^3 * $B11 -> 30317552 | E11: =SUMPRODUCT(Headcounts, AttrRates, AnnualSalaries) * (1+E$6)^3 * $B11 -> 31209189 | F11: =SUMPRODUCT(Headcounts, AttrRates, AnnualSalaries) * (1+F$6)^3 * $B11 -> 32118138 | G11: =SUMPRODUCT(Headcounts, AttrRates, AnnualSalaries) * (1+G$6)^3 * $B11 -> 33044566 | H11: =SUMPRODUCT(Headcounts, AttrRates, AnnualSalaries) * (1+H$6)^3 * $B11 -> 33988640 | I11: =SUMPRODUCT(Headcounts, AttrRates, AnnualSalaries) * (1+I$6)^3 * $B11 -> 34950527 | J11: =SUMPRODUCT(Headcounts, AttrRates, AnnualSalaries) * (1+J$6)^3 * $B11 -> 35930392

Sheet Summary
B2: Executive Summary - Workforce Risk Audit
B4: Metric | C4: Baseline | D4: Wage-Inflation | E4: Retention-Investment
B5: 4-yr replacement cost | C5: =(Headcount!C7*(Headcount!D7)*Headcount!E7*((1+WageInfl_Base)^4-1)/WageInfl_Base+Headcount!C8*(Headcount!D8+0)*Headcount!E8*((1+WageInfl_Base)^4-1)/WageInfl_Base+Headcount!C9*(Headcount!D9+0)*Headcount!E9*((1+WageInfl_Base)^4-1)/WageInfl_Base+Headcount!C10*(Headcount!D10+0)*Headcount!E10*((1+WageInfl_Base)^4-1)/WageInfl_Base+Headcount!C11*(Headcount!D11+0)*Headcount!E11*((1+WageInfl_Base)^4-1)/WageInfl_Base)*Replace_Mult -> 88363146 | D5: =(Headcount!C7*(Headcount!D7+Attr_Rise_Infl)*Headcount!E7*((1+WageInfl_High)^4-1)/WageInfl_High+Headcount!C8*(Headcount!D8+Attr_Rise_Infl)*Headcount!E8*((1+WageInfl_High)^4-1)/WageInfl_High+Headcount!C9*(Headcount!D9+Attr_Rise_Infl)*Headcount!E9*((1+WageInfl_High)^4-1)/WageInfl_High+Headcount!C10*(Headcount!D10+Attr_Rise_Infl)*Headcount!E10*((1+WageInfl_High)^4-1)/WageInfl_High+Headcount!C11*(Headcount!D11+Attr_Rise_Infl)*Headcount!E11*((1+WageInfl_High)^4-1)/WageInfl_High)*Replace_Mult -> 1.0759991e+08 | E5: =(Headcount!C7*(Target_Attr_L1)*Headcount!E7*((1+WageInfl_Base)^4-1)/WageInfl_Base+Headcount!C8*(Headcount!D8+0)*Headcount!E8*((1+WageInfl_Base)^4-1)/WageInfl_Base+Headcount!C9*(Headcount!D9+0)*Headcount!E9*((1+WageInfl_Base)^4-1)/WageInfl_Base+Headcount!C10*(Headcount!D10+0)*Headcount!E10*((1+WageInfl_Base)^4-1)/WageInfl_Base+Headcount!C11*(Headcount!D11+0)*Headcount!E11*((1+WageInfl_Base)^4-1)/WageInfl_Base)*Replace_Mult -> 75796363
B6: 4-yr retention spend | C6: 0 | D6: 0 | E6: =Headcount!C7*Retention_Invest*4 -> 10860000
B7: 4-yr TOTAL COST | C7: =C5+C6 -> 88363146 | D7: =D5+D6 -> 1.0759991e+08 | E7: =E5+E6 -> 86656363
B8: Δ vs Baseline | C8: 0 | D8: =D7-C7 -> 19236761 | E8: =E7-C7 -> -1706782.5
B11: Recommendation (Pyramid Principle top)
B12: Decision rule | C12: Cap mandatory OverTime for JobLevel 1 staff and reinvest in retention bonuses for Sales Reps and Lab Technicians. The data shows OverTime nearly doubles attrition odds; this is a higher-leverage lever than across-the-board pay raises.
B13: Why not just raise pay | C13: Logistic regression with controls shows MonthlyIncome's residual effect on attrition is small once JobLevel is held constant. Pay and JobLevel correlate at r=0.95 - the apparent 'pay effect' is largely a seniority confound.
B14: Macro hedge | C14: Wage-Inflation scenario costs ~$19M more cumulatively than Baseline. Proactive wage adjustment for retention-critical segments BEFORE inflation hits is the most important macro hedge - reactive raises during inflation are far more expensive.
B15: Confidence | C15: Logistic regression AUC = 0.748 (out-of-sample). VIF analysis confirmed multicollinearity between Income and JobLevel. Findings are robust to specification.
